h2spacex/__init__.py
h2spacex/h2_connection.py
h2spacex/h2_frames.py
h2spacex/h2_tls_connection.py
h2spacex/logger.py
h2spacex/utils.py
h2spacex-1.2.0.dist-info/LICENSE
h2spacex-1.2.0.dist-info/METADATA
h2spacex-1.2.0.dist-info/WHEEL
h2spacex-1.2.0.dist-info/top_level.txt
h2spacex-1.2.0.dist-info/RECORD
