Metadata-Version: 2.1
Name: h2spacex
Version: 1.2.0
Summary: HTTP/2 Single Packet Attack low level library based on Scapy
Home-page: https://github.com/nxenon/h2spacex
Author: nxenon
Author-email: nxenon <nasiri.aminm@gmail.com>
License: GPL-3.0
Project-URL: Homepage, https://github.com/nxenon/h2spacex
Project-URL: Bug Tracker, https://github.com/nxenon/h2spacex/issues
Project-URL: Wiki, https://github.com/nxenon/h2spacex/wiki
Project-URL: Examples, https://github.com/nxenon/h2spacex/wiki/Quick-Start-Examples
Keywords: race-condition,http2,single-packet-attack
Classifier: Programming Language :: Python :: 3
Classifier: License :: OSI Approved :: GNU General Public License v3 (GPLv3)
Classifier: Operating System :: OS Independent
Requires-Python: >=3.8.8
License-File: LICENSE
Requires-Dist: scapy (==2.5.0)
Requires-Dist: brotlipy (==0.7.0)
Requires-Dist: PySocks (==1.7.1)
